{"FOt68":{"ban":{"caseid":"FOt68"},"admin":{"name":"Cortexé\"","discrim":"1272","id":"285364390868287488"},"user":{"name":"Onewox - Türkiye","discrim":"4461","id":"364029708158894081"},"server":{"name":"ss","id":"364035817380773889","channel":"genel-sohbet","channel_id":"364035817380773891"},"reason":"deneme"},"jld4v":{"ban":{"caseid":"jld4v"},"admin":{"name":"Cortexé\"","discrim":"1272","id":"285364390868287488"},"user":{"name":"Onewox - Türkiye","discrim":"4461","id":"364029708158894081"},"server":{"name":"ss","id":"364035817380773889","channel":"agree","channel_id":"366063659161485314"},"reason":"deneme"}}